zarena-0.2.2.dist-info/METADATA
zarena-0.2.2.dist-info/WHEEL
zarena/gym_chess/test/test_castle_moves.py
zarena/gym_chess/test/test_king_moves.py
zarena/gym_chess/test/test_run_moves.py
zarena/gym_chess/test/__init__.py
zarena/gym_chess/test/test_benchmark.py
zarena/gym_chess/test/utils.py
zarena/gym_chess/test/test_basic_moves.py
zarena/gym_chess/test/test_capture_moves.py
zarena/gym_chess/test/test_squares_under_attack.py
zarena/gym_chess/__init__.py
zarena/gym_chess/examples/play_vs_self.py
zarena/gym_chess/envs/chess_env.py
zarena/gym_chess/envs/__init__.py
zarena/__init__.py
zarena/gym_blackjack/test/.keep
zarena/gym_blackjack/__init__.py
zarena/gym_blackjack/examples/.keep
zarena/gym_blackjack/envs/__init__.py
zarena/gym_blackjack/envs/blackjack_env.py
zarena/gym_tictactoe/__init__.py
zarena/gym_tictactoe/envs/__init__.py
zarena/gym_tictactoe/envs/tictactoe.py
zarena/gym_poker/__init__.py
zarena/gym_poker/envs/poker_env.py
zarena/gym_poker/envs/__init__.py
zarena/gym_checkers/__init__.py
zarena/gym_checkers/envs/checkers.py
zarena/gym_checkers/envs/__init__.py
zarena/zarena.abi3.so
zarena-0.2.2.dist-info/RECORD
